plot1qbit/1qbit.mplstyle
plot1qbit/__init__.py
plot1qbit/initiate.py
plot1qbit/util.py
plot1qbit/report_maker/__init__.py
plot1qbit/report_maker/output.py
Plot1Qbit-0.23.dist-info/LICENSE
Plot1Qbit-0.23.dist-info/METADATA
Plot1Qbit-0.23.dist-info/WHEEL
Plot1Qbit-0.23.dist-info/top_level.txt
Plot1Qbit-0.23.dist-info/RECORD
