Metadata-Version: 2.1
Name: Plot1Qbit
Version: 0.23
Summary: Set matplotlib style to conform with 1QBit's brand policies
Author: Kyle Mills
Author-email: kyle.mills@uoit.net
License-File: LICENSE
Requires-Dist: tabulate
Requires-Dist: matplotlib (>=3.1.0)
Requires-Dist: gif
Requires-Dist: tqdm
Requires-Dist: numpy
